{"nodes": [{"id": "dynamic-tools_extension", "label": "Dynamic Tools Extension", "file_type": "code", "source_file": "pi/packages/coding-agent/examples/extensions/dynamic-tools.ts", "source_location": "dynamicToolsExtension"}], "edges": [{"source": "dynamic-tools_extension", "target": "shutdown-command_extension", "relation": "conceptually_related_to", "confidence": "INFERRED", "confidence_score": 0.65, "source_file": "pi/packages/coding-agent/examples/extensions/dynamic-tools.ts", "weight": 0.6}], "hyperedges": []}