{"nodes": [{"id": "google-shared-convert-tools_test", "label": "Google Shared convertTools Test", "file_type": "code", "source_file": "pi/packages/ai/test/google-shared-convert-tools.test.ts", "source_location": null}, {"id": "json_schema_meta_key_stripping", "label": "JSON Schema meta key stripping (recursive $schema/$id/$defs)", "file_type": "code", "source_file": "pi/packages/ai/test/google-shared-convert-tools.test.ts", "source_location": null}], "edges": [{"source": "google-shared-convert-tools_test", "target": "json_schema_meta_key_stripping", "relation": "references", "confidence": "EXTRACTED", "confidence_score": 1.0, "source_file": "pi/packages/ai/test/google-shared-convert-tools.test.ts", "weight": 1.0}], "hyperedges": []}